daner/__init__.py
daner/daner.py
daner/example.py
daner/py.typed
daner-0.0.3.dist-info/WHEEL
daner-0.0.3.dist-info/METADATA
daner-0.0.3.dist-info/license_files/LICENSE
daner-0.0.3.dist-info/RECORD
