Metadata-Version: 2.1
Name: daner
Version: 0.0.3
Summary: async command line manage for fastapi
Author-email: milisp <milisp@proton.me>
Requires-Python: >=3.7
Classifier: License :: OSI Approved :: MIT License
Classifier: Operating System :: OS Independent
Classifier: Programming Language :: Python :: 3
Project-URL: Bug Tracker, https://github.com/milisp/daner/issues
Project-URL: Homepage, https://github.com/milisp/daner
